__init__.py
model/__init__.py
model/__main__.py
model/roulette_wheel.py
my_sum/__init__.py
roulette_simulator-1.0.0.dist-info/LICENSE
roulette_simulator-1.0.0.dist-info/METADATA
roulette_simulator-1.0.0.dist-info/WHEEL
roulette_simulator-1.0.0.dist-info/entry_points.txt
roulette_simulator-1.0.0.dist-info/top_level.txt
roulette_simulator-1.0.0.dist-info/RECORD
