Metadata-Version: 2.1
Name: roulette-simulator
Version: 1.0.0
Summary: Simulation of a Roulette Wheel.
Author-email: "Ryan M. Howell" <rmhowell@protonmail.com>
License: MIT License
Project-URL: repository, https://github.com/Huell-Howitzer/roulette_simulator
Project-URL: documentation, https://github.com/Huell-Howitzer/roulette_simulator.wiki
Keywords: sim,simulation,roulette
Classifier: License :: OSI Approved :: MIT License
Classifier: Programming Language :: Python
Classifier: Programming Language :: Python :: 3
Requires-Python: >=3.7
License-File: LICENSE
Provides-Extra: build
Requires-Dist: build ; extra == 'build'
Requires-Dist: twine ; extra == 'build'
Provides-Extra: dev
Requires-Dist: black ; extra == 'dev'
Requires-Dist: bumpver ; extra == 'dev'
Requires-Dist: isort ; extra == 'dev'
Requires-Dist: mypy ; extra == 'dev'
Requires-Dist: pytest ; extra == 'dev'
